fleetpy/__init__.py
fleetpy/client.py
fleetpy/unit.py
fleetpy-0.2.3.dist-info/zip-safe
fleetpy-0.2.3.dist-info/top_level.txt
fleetpy-0.2.3.dist-info/METADATA
fleetpy-0.2.3.dist-info/DESCRIPTION.rst
fleetpy-0.2.3.dist-info/metadata.json
fleetpy-0.2.3.dist-info/WHEEL
fleetpy-0.2.3.dist-info/RECORD
